CHANGES.rst
CONTRIBUTORS.rst
DEVELOP.rst
MANIFEST.in
README.rst
VERSION
setup.cfg
setup.py
docs/urlSplit.js.md
src/visaplan/__init__.py
src/visaplan.js.urlsplit.egg-info/PKG-INFO
src/visaplan.js.urlsplit.egg-info/SOURCES.txt
src/visaplan.js.urlsplit.egg-info/dependency_links.txt
src/visaplan.js.urlsplit.egg-info/entry_points.txt
src/visaplan.js.urlsplit.egg-info/namespace_packages.txt
src/visaplan.js.urlsplit.egg-info/not-zip-safe
src/visaplan.js.urlsplit.egg-info/requires.txt
src/visaplan.js.urlsplit.egg-info/top_level.txt
src/visaplan/js/__init__.py
src/visaplan/js/urlsplit/__init__.py
src/visaplan/js/urlsplit/configure.zcml
src/visaplan/js/urlsplit/interfaces.py
src/visaplan/js/urlsplit/setuphandlers.py
src/visaplan/js/urlsplit/testing.py
src/visaplan/js/urlsplit/upgrades.py
src/visaplan/js/urlsplit/upgrades.zcml
src/visaplan/js/urlsplit/browser/__init__.py
src/visaplan/js/urlsplit/browser/configure.zcml
src/visaplan/js/urlsplit/profiles/default/browserlayer.xml
src/visaplan/js/urlsplit/profiles/default/jsregistry.xml
src/visaplan/js/urlsplit/profiles/default/metadata.xml
src/visaplan/js/urlsplit/profiles/uninstall/browserlayer.xml
src/visaplan/js/urlsplit/profiles/uninstall/jsregistry.xml
src/visaplan/js/urlsplit/resource/urlSplit.js
src/visaplan/js/urlsplit/resource/urlSplit.min.js
src/visaplan/js/urlsplit/resource/urlUnsplit.js
src/visaplan/js/urlsplit/tests/__init__.py
src/visaplan/js/urlsplit/tests/test_robot.py.disabled
src/visaplan/js/urlsplit/tests/test_setup.py
src/visaplan/js/urlsplit/tests/robot/test_example.robot