Metadata-Version: 2.1
Name: visaplan.js.urlsplit
Version: 1.1.0
Summary: Plone integration of urlSplit.js
Home-page: UNKNOWN
Author: Tobias Herp
Author-email: tobias.herp@visaplan.com
License: MIT
Project-URL: Source, https://github.com/visaplan/js.urlsplit
Project-URL: Documentation, https://pypi.org/project/visaplan.js.urlsplit
Project-URL: Tracker, https://github.com/visaplan/js.urlsplit/issues
Platform: UNKNOWN
Classifier: Environment :: Web Environment
Classifier: Framework :: Plone
Classifier: Framework :: Plone :: 4.3
Classifier: Framework :: Zope
Classifier: Framework :: Zope2
Classifier: Programming Language :: Python
Classifier: Programming Language :: Python :: 2.7
Classifier: Intended Audience :: Developers
Classifier: Operating System :: OS Independent
Classifier: License :: OSI Approved :: MIT License
Provides-Extra: test
